tensor9/__init__.py
tensor9/tensor9.py
tensor9-0.1.17.dist-info/METADATA
tensor9-0.1.17.dist-info/WHEEL
tensor9-0.1.17.dist-info/top_level.txt
tensor9-0.1.17.dist-info/RECORD
