Metadata-Version: 2.1
Name: tensor9
Version: 0.1.17
